tests/examples/__init__.py
tests/examples/test_readme.py
tests/integration/__init__.py
tests/integration/test_allocation.py
tests/integration/test_broker.py
tests/integration/test_env.py
tests/integration/test_events.py
tests/integration/test_features.py
tests/integration/test_rebalancing.py
tests/integration/test_state.py
tests/integration/test_track_record.py
tests/integration/test_transmitter.py
tests/notebooks/__init__.py
tests/notebooks/test_notebooks.py
tests/regression/__init__.py
tests/regression/test_env.py
tests/unit/__init__.py
tests/unit/test_allocation.py
tests/unit/test_contracts.py
tests/unit/test_env.py
tests/unit/test_events.py
tests/unit/test_exchange.py
tests/unit/test_features.py
tests/unit/test_fees.py
tests/unit/test_library.py
tests/unit/test_metrics.py
tests/unit/test_rebalancing.py
tests/unit/test_spaces.py
tests/unit/test_state.py
tests/unit/test_trade.py
tests/unit/test_transmitter.py
tradingenv/__init__.py
tradingenv/contracts.py
tradingenv/env.py
tradingenv/events.py
tradingenv/exchange.py
tradingenv/features.py
tradingenv/library.py
tradingenv/metrics.py
tradingenv/policy.py
tradingenv/rewards.py
tradingenv/spaces.py
tradingenv/state.py
tradingenv/transmitter.py
tradingenv/broker/__init__.py
tradingenv/broker/allocation.py
tradingenv/broker/broker.py
tradingenv/broker/fees.py
tradingenv/broker/rebalancing.py
tradingenv/broker/track_record.py
tradingenv/broker/trade.py
tradingenv-0.1.3.dist-info/licenses/LICENSE.txt
tradingenv-0.1.3.dist-info/METADATA
tradingenv-0.1.3.dist-info/WHEEL
tradingenv-0.1.3.dist-info/top_level.txt
tradingenv-0.1.3.dist-info/RECORD
