Metadata-Version: 2.4
Name: tradingenv
Version: 0.1.3
Summary: Backtest trading strategies or train reinforcement learning agents with and event-driven market simulator.
Home-page: https://github.com/xaiassetmanagement/tradingenv
Author: Federico Fontana
Author-email: Federico Fontana <federico.fontana@xai-am.com>
License:                                  Apache License
Project-URL: Homepage, https://github.com/xaiassetmanagement/tradingenv
Project-URL: Documentation, https://xaiassetmanagement.github.io/tradingenv
Project-URL: Bug Tracker, https://github.com/xaiassetmanagement/tradingenv/issues
Keywords: trading,investment,finance,backtest,reinforcement-learning,gymnasium,stable-baselines3
Classifier: Programming Language :: Python :: 3
Classifier: License :: OSI Approved :: Apache Software License
Classifier: Operating System :: OS Independent
Requires-Python: >=3.9
License-File: LICENSE.txt
Requires-Dist: exchange_calendars
Requires-Dist: gymnasium
Requires-Dist: numpy
Requires-Dist: pandas
Requires-Dist: pandas_market_calendars
Requires-Dist: plotly
Requires-Dist: scikit-learn
Requires-Dist: statsmodels
Requires-Dist: tqdm
Provides-Extra: extra
Requires-Dist: yfinance; extra == "extra"
Requires-Dist: pytest; extra == "extra"
Requires-Dist: pytest-mock; extra == "extra"
Requires-Dist: pytest-cov; extra == "extra"
Requires-Dist: openpyxl; extra == "extra"
Requires-Dist: jupyterlab; extra == "extra"
Requires-Dist: nbconvert; extra == "extra"
Requires-Dist: Sphinx; extra == "extra"
Dynamic: author
Dynamic: home-page
Dynamic: keywords
Dynamic: license-file
Dynamic: provides-extra
Dynamic: requires-dist
Dynamic: summary
